{
  "message": {
    "board_info": {
      "id": 1,
      "title": "Large attorney son discover consumer tell. Then word know public outside newspaper involve.\nPer bit ",
      "description": "It likely onto carry produce.",
      "board_image_url": "https://images.unsplash.com/photo-1592204162921-d583dbd84709?crop=entropy&cs=tinysrgb&fit=crop&fm=jpg&h=900&ixid=MnwxfDB8MXxyYW5kb218MHx8c2t5fHx8fHx8MTYzNzQ2OTcxMw&ixlib=rb-1.2.1&q=80&utm_campaign=api-credit&utm_medium=referral&utm_source=unsplash_source&w=1600",
      "source": "fineartcanvas.com",
      "username": "Allison Hopkins",
      "tag_id": 1
    },
    "comments": [
      {
        "id": 1,
        "username": "Timothy Barnes",
        "profile_image_url": "http://www.torres.com/categories/tags/explore/home.jsp",
        "description": "Education southern decision we time subject else.",
        "create_at": "2021-11-21T08:36:16.241Z"
      },
      {
        "id": 2,
        "username": "Leslie Brown",
        "profile_image_url": "https://roberts.org/search/list/index.jsp",
        "description": "Right now past involve.",
        "create_at": "2021-11-21T08:36:16.242Z"
      },
      {
        "id": 3,
        "username": "Jeffrey Clayton",
        "profile_image_url": "http://www.beard-ochoa.com/category/post/",
        "description": "Various network side fill air many",
        "create_at": "2021-11-21T08:36:16.243Z"
      },
      {
        "id": 4,
        "username": "Anna Simmons",
        "profile_image_url": "http://www.ryan.biz/privacy.php",
        "description": "Free follow receive.",
        "create_at": "2021-11-21T08:36:16.243Z"
      }
    ]
  }
}
